pybeerxml/__init__.py
pybeerxml/equipment.py
pybeerxml/fermentable.py
pybeerxml/hop.py
pybeerxml/mash.py
pybeerxml/mash_step.py
pybeerxml/misc.py
pybeerxml/parser.py
pybeerxml/recipe.py
pybeerxml/style.py
pybeerxml/utils.py
pybeerxml/water.py
pybeerxml/yeast.py
pybeerxml-2.1.2.dist-info/LICENSE
pybeerxml-2.1.2.dist-info/WHEEL
pybeerxml-2.1.2.dist-info/METADATA
pybeerxml-2.1.2.dist-info/RECORD
