Metadata-Version: 2.1
Name: pybeerxml
Version: 2.1.2
Summary: A BeerXML implementation for Python
Home-page: https://github.com/hotzenklotz/pybeerxml/
License: MIT
Keywords: pybeerxml,beerxml
Author: Tom Herold
Author-email: heroldtom@gmail.com
Requires-Python: >=3.6,<4.0
Classifier: License :: OSI Approved :: MIT License
Classifier: Programming Language :: Python :: 3
Classifier: Programming Language :: Python :: 3.6
Classifier: Programming Language :: Python :: 3.7
Classifier: Programming Language :: Python :: 3.8
Classifier: Programming Language :: Python :: 3.9
Project-URL: Repository, https://github.com/hotzenklotz/pybeerxml/
